{
  "paths": {
    "/api/v1/users/register": {
      "post": {
        "tags": ["Auth"],
        "summary": "Register new user",
        "description": "Create a new user account",
        "requestBody": {
          "required": true,
          "content": {
            "application/json": {
              "schema": {
                "type": "object",
                "required": ["first_name", "last_name", "email", "password", "password_confirmation"],
                "properties": {
                  "first_name": { "type": "string" },
                  "last_name": { "type": "string" },
                  "email": { "type": "string", "format": "email" },
                  "password": { "type": "string", "minLength": 6 },
                  "password_confirmation": { "type": "string" }
                }
              }
            }
          }
        },
        "responses": {
          "201": {
            "description": "User registered successfully",
            "content": {
              "application/json": {
                "schema": {
                  "type": "object",
                  "properties": {
                    "message": { "type": "string" },
                    "data": {
                      "type": "object",
                      "properties": {
                        "access_token": { "type": "string" },
                        "refresh_token": { "type": "string" },
                        "user": { "$ref": "#/components/schemas/User" }
                      }
                    }
                  }
                }
              }
            }
          },
          "422": { "$ref": "#/components/responses/ValidationError" }
        }
      }
    },
    "/api/v1/users/login": {
      "post": {
        "tags": ["Auth"],
        "summary": "Login",
        "description": "Authenticate user with email/username and password",
        "requestBody": {
          "required": true,
          "content": {
            "application/json": {
              "schema": {
                "type": "object",
                "required": ["email", "password"],
                "properties": {
                  "email": { "type": "string" },
                  "password": { "type": "string" }
                }
              }
            }
          }
        },
        "responses": {
          "200": {
            "description": "Login successful",
            "content": {
              "application/json": {
                "schema": {
                  "type": "object",
                  "properties": {
                    "message": { "type": "string" },
                    "data": {
                      "type": "object",
                      "properties": {
                        "access_token": { "type": "string" },
                        "refresh_token": { "type": "string" },
                        "user": { "$ref": "#/components/schemas/User" }
                      }
                    }
                  }
                }
              }
            }
          },
          "401": { "$ref": "#/components/responses/Unauthorized" }
        }
      }
    },
    "/api/v1/users/refresh-token": {
      "post": {
        "tags": ["Auth"],
        "summary": "Refresh access token",
        "description": "Get new access token using refresh token",
        "requestBody": {
          "required": true,
          "content": {
            "application/json": {
              "schema": {
                "type": "object",
                "required": ["refresh_token"],
                "properties": {
                  "refresh_token": { "type": "string" }
                }
              }
            }
          }
        },
        "responses": {
          "200": {
            "description": "Token refreshed successfully",
            "content": {
              "application/json": {
                "schema": {
                  "type": "object",
                  "properties": {
                    "message": { "type": "string" },
                    "data": {
                      "type": "object",
                      "properties": {
                        "access_token": { "type": "string" },
                        "refresh_token": { "type": "string" },
                        "user": { "$ref": "#/components/schemas/User" }
                      }
                    }
                  }
                }
              }
            }
          },
          "401": { "$ref": "#/components/responses/Unauthorized" }
        }
      }
    },
    "/api/v1/users/logout": {
      "post": {
        "tags": ["Auth"],
        "summary": "Logout",
        "description": "Logout user and invalidate refresh token",
        "security": [{ "bearerAuth": [] }],
        "requestBody": {
          "required": true,
          "content": {
            "application/json": {
              "schema": {
                "type": "object",
                "required": ["refresh_token"],
                "properties": {
                  "refresh_token": { "type": "string" }
                }
              }
            }
          }
        },
        "responses": {
          "200": {
            "description": "Logout successful",
            "content": {
              "application/json": {
                "schema": {
                  "type": "object",
                  "properties": {
                    "message": { "type": "string" }
                  }
                }
              }
            }
          },
          "401": { "$ref": "#/components/responses/Unauthorized" }
        }
      }
    },
    "/api/v1/users/social-login": {
      "post": {
        "tags": ["Auth"],
        "summary": "Social Login",
        "description": "Login with Google/Facebook token",
        "requestBody": {
          "required": true,
          "content": {
            "application/json": {
              "schema": {
                "type": "object",
                "required": ["token", "provider"],
                "properties": {
                  "token": { "type": "string" },
                  "provider": { "type": "string", "enum": ["google", "facebook"] }
                }
              }
            }
          }
        },
        "responses": {
          "200": {
            "description": "Social login successful",
            "content": {
              "application/json": {
                "schema": {
                  "type": "object",
                  "properties": {
                    "message": { "type": "string" },
                    "data": {
                      "type": "object",
                      "properties": {
                        "access_token": { "type": "string" },
                        "refresh_token": { "type": "string" },
                        "user": { "$ref": "#/components/schemas/User" }
                      }
                    }
                  }
                }
              }
            }
          }
        }
      }
    },
    "/api/v1/users/forgot-password": {
      "post": {
        "tags": ["Auth"],
        "summary": "Forgot Password",
        "description": "Request password reset email",
        "requestBody": {
          "required": true,
          "content": {
            "application/json": {
              "schema": {
                "type": "object",
                "required": ["email"],
                "properties": {
                  "email": { "type": "string", "format": "email" }
                }
              }
            }
          }
        },
        "responses": {
          "200": {
            "description": "Password reset email sent",
            "content": {
              "application/json": {
                "schema": {
                  "type": "object",
                  "properties": {
                    "message": { "type": "string" }
                  }
                }
              }
            }
          }
        }
      }
    },
    "/api/v1/users/reset-password": {
      "post": {
        "tags": ["Auth"],
        "summary": "Reset Password",
        "description": "Reset password using token from email",
        "requestBody": {
          "required": true,
          "content": {
            "application/json": {
              "schema": {
                "type": "object",
                "required": ["token", "email", "password", "password_confirmation"],
                "properties": {
                  "token": { "type": "string" },
                  "email": { "type": "string", "format": "email" },
                  "password": { "type": "string", "minLength": 6 },
                  "password_confirmation": { "type": "string" }
                }
              }
            }
          }
        },
        "responses": {
          "200": {
            "description": "Password reset successful",
            "content": {
              "application/json": {
                "schema": {
                  "type": "object",
                  "properties": {
                    "message": { "type": "string" },
                    "data": {
                      "type": "object",
                      "properties": {
                        "access_token": { "type": "string" },
                        "refresh_token": { "type": "string" },
                        "user": { "$ref": "#/components/schemas/User" }
                      }
                    }
                  }
                }
              }
            }
          },
          "401": { "$ref": "#/components/responses/Unauthorized" }
        }
      }
    },
    "/api/v1/users/me": {
      "get": {
        "tags": ["Auth"],
        "summary": "Get current user profile",
        "description": "Get authenticated user's profile information",
        "security": [{ "bearerAuth": [] }],
        "responses": {
          "200": {
            "description": "User profile",
            "content": {
              "application/json": {
                "schema": {
                  "type": "object",
                  "properties": {
                    "message": { "type": "string" },
                    "data": { "$ref": "#/components/schemas/User" }
                  }
                }
              }
            }
          },
          "401": { "$ref": "#/components/responses/Unauthorized" }
        }
      },
      "patch": {
        "tags": ["Auth"],
        "summary": "Update current user profile",
        "description": "Update authenticated user's profile",
        "security": [{ "bearerAuth": [] }],
        "requestBody": {
          "content": {
            "application/json": {
              "schema": {
                "type": "object",
                "properties": {
                  "first_name": { "type": "string" },
                  "last_name": { "type": "string" },
                  "email": { "type": "string", "format": "email" },
                  "phonenumber": { "type": "string" },
                  "address": { "type": "string" },
                  "date_of_birth": { "type": "string", "format": "date" }
                }
              }
            }
          }
        },
        "responses": {
          "200": {
            "description": "Profile updated successfully",
            "content": {
              "application/json": {
                "schema": {
                  "type": "object",
                  "properties": {
                    "message": { "type": "string" },
                    "data": { "$ref": "#/components/schemas/User" }
                  }
                }
              }
            }
          },
          "401": { "$ref": "#/components/responses/Unauthorized" }
        }
      }
    },
    "/api/v1/users/me/avatar": {
      "post": {
        "tags": ["Auth"],
        "summary": "Upload user avatar",
        "description": "Upload or update user avatar",
        "security": [{ "bearerAuth": [] }],
        "requestBody": {
          "content": {
            "multipart/form-data": {
              "schema": {
                "type": "object",
                "properties": {
                  "avatar": { "type": "string", "format": "binary" },
                  "avatar_url": { "type": "string" }
                }
              }
            }
          }
        },
        "responses": {
          "200": {
            "description": "Avatar uploaded successfully",
            "content": {
              "application/json": {
                "schema": {
                  "type": "object",
                  "properties": {
                    "message": { "type": "string" },
                    "data": {
                      "type": "object",
                      "properties": {
                        "avatar_url": { "type": "string" }
                      }
                    }
                  }
                }
              }
            }
          },
          "401": { "$ref": "#/components/responses/Unauthorized" }
        }
      }
    }
  },
  "components": {
    "schemas": {
      "User": {
        "type": "object",
        "properties": {
          "_id": { "type": "string" },
          "first_name": { "type": "string" },
          "last_name": { "type": "string" },
          "full_name": { "type": "string" },
          "email": { "type": "string", "format": "email" },
          "role": { "type": "string", "enum": ["customer", "admin", "staff"] },
          "avatar": { "type": "string" },
          "address": { "type": "string" },
          "phonenumber": { "type": "string" },
          "createdAt": { "type": "string", "format": "date-time" },
          "updatedAt": { "type": "string", "format": "date-time" }
        }
      }
    },
    "responses": {
      "Unauthorized": {
        "description": "Unauthorized",
        "content": {
          "application/json": {
            "schema": {
              "type": "object",
              "properties": {
                "message": { "type": "string" }
              }
            }
          }
        }
      },
      "ValidationError": {
        "description": "Validation error",
        "content": {
          "application/json": {
            "schema": {
              "type": "object",
              "properties": {
                "message": { "type": "string" },
                "errors": {
                  "type": "array",
                  "items": {
                    "type": "object",
                    "properties": {
                      "field": { "type": "string" },
                      "message": { "type": "string" }
                    }
                  }
                }
              }
            }
          }
        }
      }
    }
  }
}
